[
{
  "pk": 1, 
  "model": "donate.donations", 
  "fields": {
    "name": "raj phull", 
    "invoice_id": "", 
    "link_url": "http://www.dealhippy.com/", 
    "link_text": "dealhippy", 
    "amount": 33.0, 
    "date": "2014-08-04", 
    "validated": true, 
    "payment": null
  }
},
{
  "pk": 2, 
  "model": "donate.donations", 
  "fields": {
    "name": "Mojo Media Group Pty Ltd", 
    "invoice_id": "", 
    "link_url": "http://www.vincentsecurity.com.au/", 
    "link_text": "Vincent Security", 
    "amount": 40.0, 
    "date": "2014-07-10", 
    "validated": true, 
    "payment": null
  }
},
{
  "pk": 3, 
  "model": "donate.donations", 
  "fields": {
    "name": "Clive Phillips", 
    "invoice_id": "", 
    "link_url": "http://www.ministryofleads.com.au/", 
    "link_text": "Ministry of Leads", 
    "amount": 45.0, 
    "date": "2014-07-08", 
    "validated": true, 
    "payment": null
  }
},
{
  "pk": 4, 
  "model": "donate.donations", 
  "fields": {
    "name": "Gorrior", 
    "invoice_id": "", 
    "link_url": "http://freepsncodes2014.com/", 
    "link_text": "free psn codes", 
    "amount": 5.0, 
    "date": "2014-06-23", 
    "validated": true, 
    "payment": null
  }
},
{
  "pk": 5, 
  "model": "donate.donations", 
  "fields": {
    "name": "Jonathan Juel", 
    "invoice_id": "", 
    "link_url": "http://newdehumidifierreviews.com/", 
    "link_text": "dehumidifier reviews", 
    "amount": 1.0, 
    "date": "2014-06-21", 
    "validated": true, 
    "payment": null
  }
},
{
  "pk": 6, 
  "model": "donate.donations", 
  "fields": {
    "name": "Mojo Media Group Pty Ltd", 
    "invoice_id": "", 
    "link_url": "http://www.murchieconstructions.com.au/", 
    "link_text": "Murchie Constructions", 
    "amount": 40.0, 
    "date": "2014-05-13", 
    "validated": true, 
    "payment": null
  }
},
{
  "pk": 7, 
  "model": "donate.donations", 
  "fields": {
    "name": "Mojo Media Group Pty Ltd", 
    "invoice_id": "", 
    "link_url": "http://www.bennettspestcontrol.com.au/", 
    "link_text": "Bennetts Pest Control Brisbane", 
    "amount": 40.0, 
    "date": "2014-05-12", 
    "validated": true, 
    "payment": null
  }
},
{
  "pk": 8, 
  "model": "donate.donations", 
  "fields": {
    "name": "SecPoint", 
    "invoice_id": "", 
    "link_url": "http://www.secpoint.com/", 
    "link_text": "SecPoint", 
    "amount": 30.0, 
    "date": "2014-04-23", 
    "validated": true, 
    "payment": null
  }
},
{
  "pk": 9, 
  "model": "donate.donations", 
  "fields": {
    "name": "Sid Pool", 
    "invoice_id": "", 
    "link_url": "", 
    "link_text": "", 
    "amount": 10.0, 
    "date": "2014-04-02", 
    "validated": true, 
    "payment": null
  }
},
{
  "pk": 10, 
  "model": "donate.donations", 
  "fields": {
    "name": "Mojo Media Group Pty Ltd", 
    "invoice_id": "", 
    "link_url": "http://www.coloursplashsigns.com.au/", 
    "link_text": " Coloursplash Signs Brisbane", 
    "amount": 40.0, 
    "date": "2014-04-01", 
    "validated": true, 
    "payment": null
  }
},
{
  "pk": 11, 
  "model": "donate.donations", 
  "fields": {
    "name": "Mojo Media Group Pty Ltd", 
    "invoice_id": "", 
    "link_url": "http://www.bargaramotel.com.au/accommodation.php", 
    "link_text": " Apartments Bargara", 
    "amount": 40.0, 
    "date": "2014-03-20", 
    "validated": true, 
    "payment": null
  }
},
{
  "pk": 12, 
  "model": "donate.donations", 
  "fields": {
    "name": "Mojo Media Group Pty Ltd", 
    "invoice_id": "", 
    "link_url": "http://www.alarmindustries.com.au/", 
    "link_text": "Security Companies Brisbane", 
    "amount": 40.0, 
    "date": "2014-03-12", 
    "validated": true, 
    "payment": null
  }
}
]
